{
  "materials": [
  {
  "item": {
   "item": "the_deep_void:refined_onyx"
      },
      "count": 3
  },
  {
   "item": {
   "item": "pointblank:guninternals"
    },
    "count": 5
  },
 
  {
   "item": {
     "item": "cw_additions:plastic_sheet"
     },
    "count": 12
  },
  {
    "item": {
      "item": "cw_additions:gun_parts"
      },
     "count": 6
   },
   {
    "item": {
      "item": "cw_additions:reinforced_barrel"
    },
    "count": 1
  }
  ],
  "result": {
    "type": "gun",
    "id": "tacz:deagle"
  }
}